vortex/__init__.py
vortex/ai/agents/__init__.py
vortex/ai/agents/memory_agent.py
vortex/ai/agents/sql_agent.py
vortex/ai/llm/__init__.py
vortex/ai/memory/__init__.py
vortex/ai/prompts/__init__.py
vortex/ai/router/__init__.py
vortex/ai/router/routes.py
vortex/ai/serve/__init__.py
vortex/ai/tools/__init__.py
vortex/ai/tools/scrapping.py
vortex/ai/tools/search.py
vortex/api/__init__.py
vortex/chat/.chainlit/config.toml
vortex/chat/.gitattributes
vortex/chat/.gitignore
vortex/chat/Dockerfile
vortex/chat/README.md
vortex/chat/agent.py
vortex/chat/app.py
vortex/chat/auth.py
vortex/chat/docs.faiss/index.faiss
vortex/chat/docs.faiss/index.pkl
vortex/chat/engine/qa_retrieval.py
vortex/chat/engine/retrieval_agent.py
vortex/chat/index_creation.py
vortex/chat/requirements.txt
vortex/datamodels/__init__.py
vortex/datamodels/wapp.py
vortex/flows/__init__.py
vortex/flows/assets/__init__.py
vortex/flows/resources/__init__.py
vortex/flows/resources/completion.py
vortex/flows/resources/orm.py
vortex/flows/resources/postgres.py
vortex/io/__init__.py
vortex/io/postgres.py
vortex/io/twilio.py
vortex_python-0.2.4.dist-info/LICENSE
vortex_python-0.2.4.dist-info/METADATA
vortex_python-0.2.4.dist-info/WHEEL
vortex_python-0.2.4.dist-info/RECORD
